discord/ext/DiscordLang/__init__.py
discord/ext/DiscordLang/lang.py
DiscordLang-0.0.1.dist-info/LICENSE
DiscordLang-0.0.1.dist-info/METADATA
DiscordLang-0.0.1.dist-info/WHEEL
DiscordLang-0.0.1.dist-info/top_level.txt
DiscordLang-0.0.1.dist-info/RECORD
